{"target":[{"name":"第1波","hang":[{"name":"","ztp":[{"name":"","number":1,"delayTime":6.919464111328125,"crtSpeed":1.0,"zType":0,"distanceZ":1.9099907875061036}]},{"name":"","ztp":[{"name":"","number":1,"delayTime":3.2021493911743166,"crtSpeed":1.0,"zType":1,"distanceZ":0.8838944435119629}]},{"name":"","ztp":[]},{"name":"","ztp":[{"name":"","number":1,"delayTime":6.850624084472656,"crtSpeed":1.0,"zType":4,"distanceZ":1.890988826751709}]},{"name":"","ztp":[]},{"name":"","ztp":[{"name":"","number":1,"delayTime":13.528017044067383,"crtSpeed":1.0,"zType":3,"distanceZ":3.7341604232788088},{"name":"","number":1,"delayTime":3.752864360809326,"crtSpeed":1.0,"zType":1,"distanceZ":1.0359091758728028}]}]}]}